LICENSE
README.md
rbh_builder/__init__.py
rbh_builder/client.py
rbh_builder/exceptions.py
rbh_builder/py.typed
rbh_builder/transport.py
rbh_builder/ws.py
rbh_builder_python-0.1.0.dist-info/METADATA
rbh_builder_python-0.1.0.dist-info/WHEEL
rbh_builder_python-0.1.0.dist-info/licenses/LICENSE
rbh_builder_python-0.1.0.dist-info/RECORD
