Metadata-Version: 2.4
Name: rbh-builder-python
Version: 0.1.0
Summary: Python client/builder for Rainbow Hospitality Gateway REST and WebSocket APIs.
Project-URL: Homepage, https://rhg.openrainbow.io
Project-URL: Repository, https://rhg.openrainbow.io
Author-email: Samuel Yip Kah Yean <samuel.yip@al-enterprise.com>
License-File: LICENSE
Requires-Python: >=3.9
Requires-Dist: requests>=2.31.0
Provides-Extra: ws
Requires-Dist: websockets>=12.0; extra == 'ws'
